MANIFEST.in
setup.py
docs/CONTRIBUTORS.txt
docs/HISTORY.txt
docs/LICENSE.ZPL
docs/LICENSE.txt
docs/README.txt
src/ztfy/__init__.py
src/ztfy.cache.egg-info/PKG-INFO
src/ztfy.cache.egg-info/SOURCES.txt
src/ztfy.cache.egg-info/dependency_links.txt
src/ztfy.cache.egg-info/namespace_packages.txt
src/ztfy.cache.egg-info/not-zip-safe
src/ztfy.cache.egg-info/requires.txt
src/ztfy.cache.egg-info/top_level.txt
src/ztfy/cache/__init__.py
src/ztfy/cache/adapter.py
src/ztfy/cache/configure.zcml
src/ztfy/cache/interfaces.py
src/ztfy/cache/meta.zcml
src/ztfy/cache/metaconfigure.py
src/ztfy/cache/metadirectives.py
src/ztfy/cache/utility.py
src/ztfy/cache/vocabulary.py
src/ztfy/cache/doctests/README.txt
src/ztfy/cache/locales/ztfy.cache.pot
src/ztfy/cache/locales/en/LC_MESSAGES/ztfy.cache.mo
src/ztfy/cache/locales/en/LC_MESSAGES/ztfy.cache.po
src/ztfy/cache/locales/fr/LC_MESSAGES/ztfy.cache.mo
src/ztfy/cache/locales/fr/LC_MESSAGES/ztfy.cache.po
src/ztfy/cache/tests/__init__.py
src/ztfy/cache/tests/test_docs.py
src/ztfy/cache/tests/test_docstrings.py