Metadata-Version: 1.1
Name: ztfy.cache
Version: 0.1.0
Summary: ZTFY package used to handle caches
Home-page: http://www.ztfy.org
Author: Thierry Florac
Author-email: tflorac@ulthar.net
License: ZPL
Platform: UNKNOWN
Classifier: Programming Language :: Python
